ptdt/__init__.py
ptdt/ptdt.py
ptdt-0.1.6.dist-info/LICENSE
ptdt-0.1.6.dist-info/WHEEL
ptdt-0.1.6.dist-info/METADATA
ptdt-0.1.6.dist-info/RECORD
