Metadata-Version: 2.1
Name: ptdt
Version: 0.1.6
Summary: PyTorch Debug Tools
Home-page: https://github.com/tanimutomo/ptdt
License: MIT
Author: tanimutomo
Author-email: tanimutomo@gmail.com
Requires-Python: >=3.8,<4.0
Classifier: License :: OSI Approved :: MIT License
Classifier: Programming Language :: Python :: 3
Classifier: Programming Language :: Python :: 3.8
Classifier: Programming Language :: Python :: 3.9
Requires-Dist: torch (>=1.0.0,<2.0.0)
Project-URL: Repository, https://github.com/tanimutomo/ptdt
